Code/Verilog_out/fir_filter.v
`timescale 1ns/1ns
module fir_filter (
    input  wire              clk,
    input  wire              reset,
    input  wire signed [7:0] din,   // Q1.7
    output reg  signed [15:0] dout  // Q1.15
);

    parameter N_TAPS = 29;

    // =========================================================
    // FIR coefficients Q1.15 (fc = 3 Hz, COPY từ MATLAB)
    // =========================================================
    reg signed [15:0] h [0:N_TAPS-1];
    initial begin
        h[0]  = 16'h0085; h[1]  = 16'h009F; h[2]  = 16'h00E3; h[3]  = 16'h0152;
        h[4]  = 16'h01EB; h[5]  = 16'h02A8; h[6]  = 16'h0382; h[7]  = 16'h046E;
        h[8]  = 16'h0560; h[9]  = 16'h064A; h[10] = 16'h0721; h[11] = 16'h07D6;
        h[12] = 16'h0861; h[13] = 16'h08B7; h[14] = 16'h08D4; h[15] = 16'h08B7;
        h[16] = 16'h0861; h[17] = 16'h07D6; h[18] = 16'h0721; h[19] = 16'h064A;
        h[20] = 16'h0560; h[21] = 16'h046E; h[22] = 16'h0382; h[23] = 16'h02A8;
        h[24] = 16'h01EB; h[25] = 16'h0152; h[26] = 16'h00E3; h[27] = 16'h009F;
        h[28] = 16'h0085;
    end

    // =========================================================
    // Shift register (Q1.7)
    // =========================================================
    reg signed [7:0] sr [0:N_TAPS-1];
    integer i;

    // =========================================================
    // Multiply-Accumulate + Saturation
    // =========================================================
    reg signed [31:0] acc;
    reg signed [31:0] shifted;
    reg signed [15:0] tmp;

    always @(posedge clk or posedge reset) begin
        if (reset) begin
            for (i = 0; i < N_TAPS; i = i + 1)
                sr[i] <= 0;
            dout <= 0;
        end else begin
            // shift register
            for (i = N_TAPS-1; i > 0; i = i - 1)
                sr[i] <= sr[i-1];
            sr[0] <= din;

            // multiply-accumulate
            acc = 0;
            for (i = 0; i < N_TAPS; i = i + 1)
                acc = acc + sr[i] * h[i]; // giữ đúng thứ tự hệ số

            // scale Q1.7 * Q1.15 = Q2.22 → Q1.15
            shifted = acc >>> 7;

            // saturation
            if (shifted > 32767)
                dout <= 16'sh7FFF;
            else if (shifted < -32768)
                dout <= -16'sh8000;
            else begin
                tmp = shifted[15:0];
                dout <= tmp;
            end
        end
    end

endmodule

Code/Verilog_out/fir_tb.v
`timescale 1ns/1ns
module fir_tb;

    reg clk = 0;
    always #5 clk = ~clk;   // 10 ns period

    reg reset;
    reg signed [7:0] din;
    wire signed [15:0] dout;

    fir_filter dut (
        .clk(clk),
        .reset(reset),
        .din(din),
        .dout(dout)
    );

    integer fin, fout;
    reg [7:0] byte_val;
    reg signed [7:0] mem[0:200000]; 
    integer i, num_samples, code;

    localparam FIR_TAPS = 29;
    localparam LATENCY  = (FIR_TAPS-1)/2; // = 14

    initial begin
        // dump waveform
        $dumpfile("fir_wave.vcd");
        $dumpvars(0, fir_tb);

        // --- đọc input hex ---
        $display("FIR TB: reading input file...");
        fin = $fopen("ECG_Input.txt", "r");
        if (fin == 0) begin
            $display("Cannot open input file");
            $finish;
        end

        i = 0;
        code = $fscanf(fin, "%h", byte_val);
        while (code == 1) begin
            mem[i] = $signed(byte_val);   // Q1.7 signed
            i = i + 1;
            code = $fscanf(fin, "%h", byte_val);
        end
        $fclose(fin);
        num_samples = i;
        $display("Loaded %0d samples", num_samples);

        fout = $fopen("Output_V.txt", "w");

        // --- reset & prime ---
        reset = 1;
        din   = 0;
        repeat (3) @(posedge clk);
        reset = 0;

        // --- main processing: drive trước, ghi sau LATENCY ---
        for (i = 0; i < num_samples; i = i + 1) begin
            // lái input cho chu kỳ kế tiếp
            din = mem[i];
            @(posedge clk);

            // sau khi qua đủ LATENCY chu kỳ, dout mới hợp lệ để ghi
            if (i >= LATENCY)
                $fwrite(fout, "%04X\n", dout[15:0]); // signed 16-bit hex
        end

        // --- flush pipeline: thêm LATENCY chu kỳ để xả hết ---
        for (i = 0; i < LATENCY; i = i + 1) begin
            din = 0; // hoặc giữ mem[num_samples-1], tuỳ bạn
            @(posedge clk);
            $fwrite(fout, "%04X\n", dout[15:0]);
        end

        $fclose(fout);
        $display("Simulation output written to Output_V.txt");
        $finish;
    end
endmodule

Code/Verilog_out/fir_wave.vcd
$date
	Wed Jun 03 19:59:14 2026
$end
$version
	Icarus Verilog
$end
$timescale
	1ns
$end
$scope module fir_tb $end
$var wire 16 ! dout [15:0] $end
$var parameter 32 " FIR_TAPS $end
$var parameter 33 # LATENCY $end
$var reg 8 $ byte_val [7:0] $end
$var reg 1 % clk $end
$var reg 8 & din [7:0] $end
$var reg 1 ' reset $end
$var integer 32 ( code [31:0] $end
$var integer 32 ) fin [31:0] $end
$var integer 32 * fout [31:0] $end
$var integer 32 + i [31:0] $end
$var integer 32 , num_samples [31:0] $end
$scope module dut $end
$var wire 1 % clk $end
$var wire 8 - din [7:0] $end
$var wire 1 ' reset $end
$var parameter 32 . N_TAPS $end
$var reg 32 / acc [31:0] $end
$var reg 16 0 dout [15:0] $end
$var reg 32 1 shifted [31:0] $end
$var reg 16 2 tmp [15:0] $end
$var integer 32 3 i [31:0] $end
$upscope $end
$upscope $end
$enddefinitions $end
$comment Show the parameter values. $end
$dumpall
b11101 .
b1110 #
b11101 "
$end
#0
$dumpvars
b11101 3
bx 2
bx 1
b0 0
bx /
b0 -
b11001001 ,
b11001001 +
b10000000000000000000000000000011 *
b10000000000000000000000000000011 )
b0 (
1'
b0 &
0%
b10 $
b0 !
$end
#5
b11101 3
1%
#10
0%
#15
b11101 3
1%
#20
0%
#25
b0 2
b0 1
b0 /
b11101 3
b110 &
b110 -
b0 +
0'
1%
#30
0%
#35
b110 !
b110 0
b110 2
b110 1
b1100011110 /
b11101 3
b101001 &
b101001 -
b1 +
1%
#40
0%
#45
b110010 !
b110010 0
b110010 2
b110010 1
b1100100000111 /
b11101 3
b1011 &
b1011 -
b10 +
1%
#50
0%
#55
b1001001 !
b1001001 0
b1001001 2
b1001001 1
b10010010000000 /
b11101 3
b101111 &
b101111 -
b11 +
1%
#60
0%
#65
b10010111 !
b10010111 0
b10010111 2
b10010111 1
b100101110000111 /
b11101 3
b100000 &
b100000 -
b100 +
1%
#70
0%
#75
b11110010 !
b11110010 0
b11110010 2
b11110010 1
b111100100110110 /
b11101 3
b11111110 &
b11111110 -
b101 +
1%
#80
0%
#85
b101010011 !
b101010011 0
b101010011 2
b101010011 1
b1010100110011100 /
b11101 3
b11110111 &
b11110111 -
b110 +
1%
#90
0%
#95
b111010111 !
b111010111 0
b111010111 2
b111010111 1
b1110101110010000 /
b11101 3
b11110101 &
b11110101 -
b111 +
1%
#100
0%
#105
b1001111101 !
b1001111101 0
b1001111101 2
b1001111101 1
b10011111011101111 /
b11101 3
b11010 &
b11010 -
b1000 +
1%
#110
0%
#115
b1101100101 !
b1101100101 0
b1101100101 2
b1101100101 1
b11011001010111010 /
b11101 3
b100000 &
b100000 -
b1001 +
1%
#120
0%
#125
b10001101000 !
b10001101000 0
b10001101000 2
b10001101000 1
b100011010000000001 /
b11101 3
b1001 &
b1001 -
b1010 +
1%
#130
0%
#135
b10101100101 !
b10101100101 0
b10101100101 2
b10101100101 1
b101011001010110100 /
b11101 3
b1001101 &
b1001101 -
b1011 +
1%
#140
0%
#145
b11010110110 !
b11010110110 0
b11010110110 2
b11010110110 1
b110101101100100010 /
b11101 3
b1000010 &
b1000010 -
b1100 +
1%
#150
0%
#155
b100000001100 !
b100000001100 0
b100000001100 2
b100000001100 1
b1000000011000011101 /
b11101 3
b111100 &
b111100 -
b1101 +
1%
#160
0%
#165
b100101110111 !
b100101110111 0
b100101110111 2
b100101110111 1
b1001011101111100011 /
b11101 3
b111011 &
b111011 -
b1110 +
1%
#170
0%
#175
b101100000101 !
b101100000101 0
b101100000101 2
b101100000101 1
b1011000001011000000 /
b11101 3
b100000 &
b100000 -
b1111 +
1%
#180
0%
#185
b110010100010 !
b110010100010 0
b110010100010 2
b110010100010 1
b1100101000101001110 /
b11101 3
b10000 &
b10000 -
b10000 +
1%
#190
0%
#195
b111001011010 !
b111001011010 0
b111001011010 2
b111001011010 1
b1110010110101010000 /
b11101 3
b11000 &
b11000 -
b10001 +
1%
#200
0%
#205
b1000000111110 !
b1000000111110 0
b1000000111110 2
b1000000111110 1
b10000001111100010001 /
b11101 3
b11001 &
b11001 -
b10010 +
1%
#210
0%
#215
b1001000111011 !
b1001000111011 0
b1001000111011 2
b1001000111011 1
b10010001110110111001 /
b11101 3
b100110 &
b100110 -
b10011 +
1%
#220
0%
#225
b1010001010011 !
b1010001010011 0
b1010001010011 2
b1010001010011 1
b10100010100110010011 /
b11101 3
b110011 &
b110011 -
b10100 +
1%
#230
0%
#235
b1011001111000 !
b1011001111000 0
b1011001111000 2
b1011001111000 1
b10110011110001010111 /
b11101 3
b110100 &
b110100 -
b10101 +
1%
#240
0%
#245
b1100010011001 !
b1100010011001 0
b1100010011001 2
b1100010011001 1
b11000100110011101000 /
b11101 3
b1010110 &
b1010110 -
b10110 +
1%
#250
0%
#255
b1101011010001 !
b1101011010001 0
b1101011010001 2
b1101011010001 1
b11010110100010101001 /
b11101 3
b1100010 &
b1100010 -
b10111 +
1%
#260
0%
#265
b1110100001100 !
b1110100001100 0
b1110100001100 2
b1110100001100 1
b11101000011000110001 /
b11101 3
b1001100 &
b1001100 -
b11000 +
1%
#270
0%
#275
b1111100110001 !
b1111100110001 0
b1111100110001 2
b1111100110001 1
b11111001100010001000 /
b11101 3
b1000000 &
b1000000 -
b11001 +
1%
#280
0%
#285
b10000101010001 !
b10000101010001 0
b10000101010001 2
b10000101010001 1
b100001010100011001111 /
b11101 3
b101100 &
b101100 -
b11010 +
1%
#290
0%
#295
b10001101101011 !
b10001101101011 0
b10001101101011 2
b10001101101011 1
b100011011010110000000 /
b11101 3
b10110 &
b10110 -
b11011 +
1%
#300
0%
#305
b10010101111001 !
b10010101111001 0
b10010101111001 2
b10010101111001 1
b100101011110011000100 /
b11101 3
b11110 &
b11110 -
b11100 +
1%
#310
0%
#315
b10011110010001 !
b10011110010001 0
b10011110010001 2
b10011110010001 1
b100111100100010100010 /
b11101 3
b100000 &
b100000 -
b11101 +
1%
#320
0%
#325
b10100110011001 !
b10100110011001 0
b10100110011001 2
b10100110011001 1
b101001100110011001001 /
b11101 3
b1000110 &
b1000110 -
b11110 +
1%
#330
0%
#335
b10101110000110 !
b10101110000110 0
b10101110000110 2
b10101110000110 1
b101011100001100100000 /
b11101 3
b1000101 &
b1000101 -
b11111 +
1%
#340
0%
#345
b10110101100101 !
b10110101100101 0
b10110101100101 2
b10110101100101 1
b101101011001011101010 /
b11101 3
b1010011 &
b1010011 -
b100000 +
1%
#350
0%
#355
b10111011111111 !
b10111011111111 0
b10111011111111 2
b10111011111111 1
b101110111111111000011 /
b11101 3
b1010111 &
b1010111 -
b100001 +
1%
#360
0%
#365
b11000001111010 !
b11000001111010 0
b11000001111010 2
b11000001111010 1
b110000011110101010011 /
b11101 3
b110101 &
b110101 -
b100010 +
1%
#370
0%
#375
b11000111001101 !
b11000111001101 0
b11000111001101 2
b11000111001101 1
b110001110011011110011 /
b11101 3
b1010010 &
b1010010 -
b100011 +
1%
#380
0%
#385
b11001100101100 !
b11001100101100 0
b11001100101100 2
b11001100101100 1
b110011001011000010010 /
b11101 3
b110101 &
b110101 -
b100100 +
1%
#390
0%
#395
b11010001100100 !
b11010001100100 0
b11010001100100 2
b11010001100100 1
b110100011001000010010 /
b11101 3
b11110 &
b11110 -
b100101 +
1%
#400
0%
#405
b11010101011110 !
b11010101011110 0
b11010101011110 2
b11010101011110 1
b110101010111100101000 /
b11101 3
b110110 &
b110110 -
b100110 +
1%
#410
0%
#415
b11011001100100 !
b11011001100100 0
b11011001100100 2
b11011001100100 1
b110110011001001111110 /
b11101 3
b100001 &
b100001 -
b100111 +
1%
#420
0%
#425
b11011101100010 !
b11011101100010 0
b11011101100010 2
b11011101100010 1
b110111011000100110110 /
b11101 3
b1000110 &
b1000110 -
b101000 +
1%
#430
0%
#435
b11100000101011 !
b11100000101011 0
b11100000101011 2
b11100000101011 1
b111000001010111001001 /
b11101 3
b1011000 &
b1011000 -
b101001 +
1%
#440
0%
#445
b11100011101110 !
b11100011101110 0
b11100011101110 2
b11100011101110 1
b111000111011101111111 /
b11101 3
b1101011 &
b1101011 -
b101010 +
1%
#450
0%
#455
b11100110100111 !
b11100110100111 0
b11100110100111 2
b11100110100111 1
b111001101001110111110 /
b11101 3
b101011 +
1%
#460
0%
#465
b11101001000101 !
b11101001000101 0
b11101001000101 2
b11101001000101 1
b111010010001010101111 /
b11101 3
b1010011 &
b1010011 -
b101100 +
1%
#470
0%
#475
b11101011011100 !
b11101011011100 0
b11101011011100 2
b11101011011100 1
b111010110111001010110 /
b11101 3
b1001010 &
b1001010 -
b101101 +
1%
#480
0%
#485
b11101110001000 !
b11101110001000 0
b11101110001000 2
b11101110001000 1
b111011100010000100001 /
b11101 3
b110110 &
b110110 -
b101110 +
1%
#490
0%
#495
b11110000110110 !
b11110000110110 0
b11110000110110 2
b11110000110110 1
b111100001101100001010 /
b11101 3
b110011 &
b110011 -
b101111 +
1%
#500
0%
#505
b11110100000111 !
b11110100000111 0
b11110100000111 2
b11110100000111 1
b111101000001111110110 /
b11101 3
b111000 &
b111000 -
b110000 +
1%
#510
0%
#515
b11110111111010 !
b11110111111010 0
b11110111111010 2
b11110111111010 1
b111101111110100101110 /
b11101 3
b1000100 &
b1000100 -
b110001 +
1%
#520
0%
#525
b11111100001011 !
b11111100001011 0
b11111100001011 2
b11111100001011 1
b111111000010111011010 /
b11101 3
b1000010 &
b1000010 -
b110010 +
1%
#530
0%
#535
b100000000110000 !
b100000000110000 0
b100000000110000 2
b100000000110000 1
b1000000001100001010000 /
b11101 3
b1011111 &
b1011111 -
b110011 +
1%
#540
0%
#545
b100000101010110 !
b100000101010110 0
b100000101010110 2
b100000101010110 1
b1000001010101101110101 /
b11101 3
b1011101 &
b1011101 -
b110100 +
1%
#550
0%
#555
b100001001100100 !
b100001001100100 0
b100001001100100 2
b100001001100100 1
b1000010011001000101100 /
b11101 3
b110101 +
1%
#560
0%
#565
b100001101110011 !
b100001101110011 0
b100001101110011 2
b100001101110011 1
b1000011011100111101100 /
b11101 3
b110110 +
1%
#570
0%
#575
b100010001110111 !
b100010001110111 0
b100010001110111 2
b100010001110111 1
b1000100011101110111001 /
b11101 3
b1011011 &
b1011011 -
b110111 +
1%
#580
0%
#585
b100010101111010 !
b100010101111010 0
b100010101111010 2
b100010101111010 1
b1000101011110100110110 /
b11101 3
b101111 &
b101111 -
b111000 +
1%
#590
0%
#595
b100011001011110 !
b100011001011110 0
b100011001011110 2
b100011001011110 1
b1000110010111101010111 /
b11101 3
b111001 +
1%
#600
0%
#605
b100011100110111 !
b100011100110111 0
b100011100110111 2
b100011100110111 1
b1000111001101111011110 /
b11101 3
b101000 &
b101000 -
b111010 +
1%
#610
0%
#615
b100100000000001 !
b100100000000001 0
b100100000000001 2
b100100000000001 1
b1001000000000011110110 /
b11101 3
b1000001 &
b1000001 -
b111011 +
1%
#620
0%
#625
b100100010101101 !
b100100010101101 0
b100100010101101 2
b100100010101101 1
b1001000101011011011111 /
b11101 3
b111100 &
b111100 -
b111100 +
1%
#630
0%
#635
b100100100110101 !
b100100100110101 0
b100100100110101 2
b100100100110101 1
b1001001001101011010101 /
b11101 3
b1011010 &
b1011010 -
b111101 +
1%
#640
0%
#645
b100100110100010 !
b100100110100010 0
b100100110100010 2
b100100110100010 1
b1001001101000100110100 /
b11101 3
b1101010 &
b1101010 -
b111110 +
1%
#650
0%
#655
b100100111100111 !
b100100111100111 0
b100100111100111 2
b100100111100111 1
b1001001111001111011101 /
b11101 3
b1101111 &
b1101111 -
b111111 +
1%
#660
0%
#665
b100101000101000 !
b100101000101000 0
b100101000101000 2
b100101000101000 1
b1001010001010000110011 /
b11101 3
b1100111 &
b1100111 -
b1000000 +
1%
#670
0%
#675
b100101000100101 !
b100101000100101 0
b100101000100101 2
b100101000100101 1
b1001010001001011011100 /
b11101 3
b1000100 &
b1000100 -
b1000001 +
1%
#680
0%
#685
b100101000010000 !
b100101000010000 0
b100101000010000 2
b100101000010000 1
b1001010000100001110001 /
b11101 3
b11111 &
b11111 -
b1000010 +
1%
#690
0%
#695
b100100111110011 !
b100100111110011 0
b100100111110011 2
b100100111110011 1
b1001001111100110011100 /
b11101 3
b11010 &
b11010 -
b1000011 +
1%
#700
0%
#705
b100100111000100 !
b100100111000100 0
b100100111000100 2
b100100111000100 1
b1001001110001001100001 /
b11101 3
b10101 &
b10101 -
b1000100 +
1%
#710
0%
#715
b100100110101110 !
b100100110101110 0
b100100110101110 2
b100100110101110 1
b1001001101011101100101 /
b11101 3
b1000100 &
b1000100 -
b1000101 +
1%
#720
0%
#725
b100100110100010 !
b100100110100010 0
b100100110100010 2
b100100110100010 1
b1001001101000100110111 /
b11101 3
b110110 &
b110110 -
b1000110 +
1%
#730
0%
#735
b100100101100110 !
b100100101100110 0
b100100101100110 2
b100100101100110 1
b1001001011001100011011 /
b11101 3
b1010110 &
b1010110 -
b1000111 +
1%
#740
0%
#745
b100100100011010 !
b100100100011010 0
b100100100011010 2
b100100100011010 1
b1001001000110100111101 /
b11101 3
b1001000 +
1%
#750
0%
#755
b100100010100101 !
b100100010100101 0
b100100010100101 2
b100100010100101 1
b1001000101001011100010 /
b11101 3
b1100000 &
b1100000 -
b1001001 +
1%
#760
0%
#765
b100100000101011 !
b100100000101011 0
b100100000101011 2
b100100000101011 1
b1001000001010111011000 /
b11101 3
b1000001 &
b1000001 -
b1001010 +
1%
#770
0%
#775
b100011101111100 !
b100011101111100 0
b100011101111100 2
b100011101111100 1
b1000111011111000110011 /
b11101 3
b100110 &
b100110 -
b1001011 +
1%
#780
0%
#785
b100011010110101 !
b100011010110101 0
b100011010110101 2
b100011010110101 1
b1000110101101010001000 /
b11101 3
b10001 &
b10001 -
b1001100 +
1%
#790
0%
#795
b100010111010010 !
b100010111010010 0
b100010111010010 2
b100010111010010 1
b1000101110100100000100 /
b11101 3
b11000 &
b11000 -
b1001101 +
1%
#800
0%
#805
b100010011101001 !
b100010011101001 0
b100010011101001 2
b100010011101001 1
b1000100111010011100011 /
b11101 3
b1111 &
b1111 -
b1001110 +
1%
#810
0%
#815
b100001111011110 !
b100001111011110 0
b100001111011110 2
b100001111011110 1
b1000011110111100110101 /
b11101 3
b11001 &
b11001 -
b1001111 +
1%
#820
0%
#825
b100001011001010 !
b100001011001010 0
b100001011001010 2
b100001011001010 1
b1000010110010100110011 /
b11101 3
b111011 &
b111011 -
b1010000 +
1%
#830
0%
#835
b100000110011001 !
b100000110011001 0
b100000110011001 2
b100000110011001 1
b1000001100110010100000 /
b11101 3
b1000000 &
b1000000 -
b1010001 +
1%
#840
0%
#845
b100000001000110 !
b100000001000110 0
b100000001000110 2
b100000001000110 1
b1000000010001101101001 /
b11101 3
b1001001 &
b1001001 -
b1010010 +
1%
#850
0%
#855
b11111011010100 !
b11111011010100 0
b11111011010100 2
b11111011010100 1
b111110110101001101010 /
b11101 3
b1010110 &
b1010110 -
b1010011 +
1%
#860
0%
#865
b11110101001111 !
b11110101001111 0
b11110101001111 2
b11110101001111 1
b111101010011111110011 /
b11101 3
b101110 &
b101110 -
b1010100 +
1%
#870
0%
#875
b11101110010001 !
b11101110010001 0
b11101110010001 2
b11101110010001 1
b111011100100011110011 /
b11101 3
b101010 &
b101010 -
b1010101 +
1%
#880
0%
#885
b11100111111101 !
b11100111111101 0
b11100111111101 2
b11100111111101 1
b111001111111010000100 /
b11101 3
b10110 &
b10110 -
b1010110 +
1%
#890
0%
#895
b11100001100110 !
b11100001100110 0
b11100001100110 2
b11100001100110 1
b111000011001100001011 /
b11101 3
b11111101 &
b11111101 -
b1010111 +
1%
#900
0%
#905
b11011011011110 !
b11011011011110 0
b11011011011110 2
b11011011011110 1
b110110110111100010110 /
b11101 3
b11111111 &
b11111111 -
b1011000 +
1%
#910
0%
#915
b11010101011111 !
b11010101011111 0
b11010101011111 2
b11010101011111 1
b110101010111111100101 /
b11101 3
b11111010 &
b11111010 -
b1011001 +
1%
#920
0%
#925
b11001111111001 !
b11001111111001 0
b11001111111001 2
b11001111111001 1
b110011111110011100100 /
b11101 3
b1011 &
b1011 -
b1011010 +
1%
#930
0%
#935
b11001010001100 !
b11001010001100 0
b11001010001100 2
b11001010001100 1
b110010100011001000110 /
b11101 3
b101001 &
b101001 -
b1011011 +
1%
#940
0%
#945
b11000100011101 !
b11000100011101 0
b11000100011101 2
b11000100011101 1
b110001000111011100010 /
b11101 3
b111001 &
b111001 -
b1011100 +
1%
#950
0%
#955
b10111110011000 !
b10111110011000 0
b10111110011000 2
b10111110011000 1
b101111100110001111110 /
b11101 3
b1001011 &
b1001011 -
b1011101 +
1%
#960
0%
#965
b10111000000111 !
b10111000000111 0
b10111000000111 2
b10111000000111 1
b101110000001111011100 /
b11101 3
b11010 &
b11010 -
b1011110 +
1%
#970
0%
#975
b10110001001000 !
b10110001001000 0
b10110001001000 2
b10110001001000 1
b101100010010001011101 /
b11101 3
b1110 &
b1110 -
b1011111 +
1%
#980
0%
#985
b10101010010110 !
b10101010010110 0
b10101010010110 2
b10101010010110 1
b101010100101100010110 /
b11101 3
b11110110 &
b11110110 -
b1100000 +
1%
#990
0%
#995
b10100011010001 !
b10100011010001 0
b10100011010001 2
b10100011010001 1
b101000110100011111100 /
b11101 3
b11010100 &
b11010100 -
b1100001 +
1%
#1000
0%
#1005
b10011011111100 !
b10011011111100 0
b10011011111100 2
b10011011111100 1
b100110111111001010010 /
b11101 3
b11100001 &
b11100001 -
b1100010 +
1%
#1010
0%
#1015
b10010100001010 !
b10010100001010 0
b10010100001010 2
b10010100001010 1
b100101000010100101001 /
b11101 3
b11011100 &
b11011100 -
b1100011 +
1%
#1020
0%
#1025
b10001100010101 !
b10001100010101 0
b10001100010101 2
b10001100010101 1
b100011000101010000100 /
b11101 3
b1001 &
b1001 -
b1100100 +
1%
#1030
0%
#1035
b10000100001101 !
b10000100001101 0
b10000100001101 2
b10000100001101 1
b100001000011010110100 /
b11101 3
b111 &
b111 -
b1100101 +
1%
#1040
0%
#1045
b1111011010011 !
b1111011010011 0
b1111011010011 2
b1111011010011 1
b11110110100111100111 /
b11101 3
b11011 &
b11011 -
b1100110 +
1%
#1050
0%
#1055
b1110001101011 !
b1110001101011 0
b1110001101011 2
b1110001101011 1
b11100011010111000100 /
b11101 3
b10010 &
b10010 -
b1100111 +
1%
#1060
0%
#1065
b1100111100100 !
b1100111100100 0
b1100111100100 2
b1100111100100 1
b11001111001000011101 /
b11101 3
b1101 &
b1101 -
b1101000 +
1%
#1070
0%
#1075
b1011101001101 !
b1011101001101 0
b1011101001101 2
b1011101001101 1
b10111010011010111111 /
b11101 3
b11101110 &
b11101110 -
b1101001 +
1%
#1080
0%
#1085
b1010010011111 !
b1010010011111 0
b1010010011111 2
b1010010011111 1
b10100100111111000000 /
b11101 3
b11100100 &
b11100100 -
b1101010 +
1%
#1090
0%
#1095
b1000111101000 !
b1000111101000 0
b1000111101000 2
b1000111101000 1
b10001111010001111110 /
b11101 3
b11011001 &
b11011001 -
b1101011 +
1%
#1100
0%
#1105
b111101000111 !
b111101000111 0
b111101000111 2
b111101000111 1
b1111010001110110001 /
b11101 3
b11100001 &
b11100001 -
b1101100 +
1%
#1110
0%
#1115
b110011000011 !
b110011000011 0
b110011000011 2
b110011000011 1
b1100110000110100001 /
b11101 3
b11010110 &
b11010110 -
b1101101 +
1%
#1120
0%
#1125
b101000101110 !
b101000101110 0
b101000101110 2
b101000101110 1
b1010001011100001111 /
b11101 3
b11010010 &
b11010010 -
b1101110 +
1%
#1130
0%
#1135
b11110100010 !
b11110100010 0
b11110100010 2
b11110100010 1
b111101000100110001 /
b11101 3
b11110000 &
b11110000 -
b1101111 +
1%
#1140
0%
#1145
b10100101110 !
b10100101110 0
b10100101110 2
b10100101110 1
b101001011100101101 /
b11101 3
b10001 &
b10001 -
b1110000 +
1%
#1150
0%
#1155
b1011000011 !
b1011000011 0
b1011000011 2
b1011000011 1
b10110000111001111 /
b11101 3
b11110101 &
b11110101 -
b1110001 +
1%
#1160
0%
#1165
b1011010 !
b1011010 0
b1011010 2
b1011010 1
b10110100100100 /
b11101 3
b11111101 &
b11111101 -
b1110010 +
1%
#1170
0%
#1175
b1111110111111100 !
b1111110111111100 0
b1111110111111100 2
b11111111111111111111110111111100 1
b11111111111111101111111000101000 /
b11101 3
b11011111 &
b11011111 -
b1110011 +
1%
#1180
0%
#1185
b1111101110011111 !
b1111101110011111 0
b1111101110011111 2
b11111111111111111111101110011111 1
b11111111111111011100111111001100 /
b11101 3
b11011000 &
b11011000 -
b1110100 +
1%
#1190
0%
#1195
b1111100101110000 !
b1111100101110000 0
b1111100101110000 2
b11111111111111111111100101110000 1
b11111111111111001011100000011000 /
b11101 3
b10100110 &
b10100110 -
b1110101 +
1%
#1200
0%
#1205
b1111011100110000 !
b1111011100110000 0
b1111011100110000 2
b11111111111111111111011100110000 1
b11111111111110111001100000000001 /
b11101 3
b10110111 &
b10110111 -
b1110110 +
1%
#1210
0%
#1215
b1111010100101010 !
b1111010100101010 0
b1111010100101010 2
b11111111111111111111010100101010 1
b11111111111110101001010100011110 /
b11101 3
b10110110 &
b10110110 -
b1110111 +
1%
#1220
0%
#1225
b1111001100101001 !
b1111001100101001 0
b1111001100101001 2
b11111111111111111111001100101001 1
b11111111111110011001010010010100 /
b11101 3
b11110011 &
b11110011 -
b1111000 +
1%
#1230
0%
#1235
b1111000101001100 !
b1111000101001100 0
b1111000101001100 2
b11111111111111111111000101001100 1
b11111111111110001010011001110100 /
b11101 3
b11101110 &
b11101110 -
b1111001 +
1%
#1240
0%
#1245
b1110111101001111 !
b1110111101001111 0
b1110111101001111 2
b11111111111111111110111101001111 1
b11111111111101111010011110000101 /
b11101 3
b11111110 &
b11111110 -
b1111010 +
1%
#1250
0%
#1255
b1110110100111001 !
b1110110100111001 0
b1110110100111001 2
b11111111111111111110110100111001 1
b11111111111101101001110010010100 /
b11101 3
b11100010 &
b11100010 -
b1111011 +
1%
#1260
0%
#1265
b1110101100100000 !
b1110101100100000 0
b1110101100100000 2
b11111111111111111110101100100000 1
b11111111111101011001000000011111 /
b11101 3
b11011010 &
b11011010 -
b1111100 +
1%
#1270
0%
#1275
b1110100011111110 !
b1110100011111110 0
b1110100011111110 2
b11111111111111111110100011111110 1
b11111111111101000111111100010110 /
b11101 3
b11001000 &
b11001000 -
b1111101 +
1%
#1280
0%
#1285
b1110011011011111 !
b1110011011011111 0
b1110011011011111 2
b11111111111111111110011011011111 1
b11111111111100110110111111011100 /
b11101 3
b11000010 &
b11000010 -
b1111110 +
1%
#1290
0%
#1295
b1110010011101110 !
b1110010011101110 0
b1110010011101110 2
b11111111111111111110010011101110 1
b11111111111100100111011100010100 /
b11101 3
b10100110 &
b10100110 -
b1111111 +
1%
#1300
0%
#1305
b1110001011101111 !
b1110001011101111 0
b1110001011101111 2
b11111111111111111110001011101111 1
b11111111111100010111011111110001 /
b11101 3
b10101111 &
b10101111 -
b10000000 +
1%
#1310
0%
#1315
b1110000100100010 !
b1110000100100010 0
b1110000100100010 2
b11111111111111111110000100100010 1
b11111111111100001001000100000111 /
b11101 3
b10011100 &
b10011100 -
b10000001 +
1%
#1320
0%
#1325
b1101111100101011 !
b1101111100101011 0
b1101111100101011 2
b11111111111111111101111100101011 1
b11111111111011111001010111010111 /
b11101 3
b10111111 &
b10111111 -
b10000010 +
1%
#1330
0%
#1335
b1101110101100010 !
b1101110101100010 0
b1101110101100010 2
b11111111111111111101110101100010 1
b11111111111011101011000101001001 /
b11101 3
b11001100 &
b11001100 -
b10000011 +
1%
#1340
0%
#1345
b1101101110000100 !
b1101101110000100 0
b1101101110000100 2
b11111111111111111101101110000100 1
b11111111111011011100001001001110 /
b11101 3
b11001110 &
b11001110 -
b10000100 +
1%
#1350
0%
#1355
b1101100110011000 !
b1101100110011000 0
b1101100110011000 2
b11111111111111111101100110011000 1
b11111111111011001100110001010010 /
b11101 3
b11100011 &
b11100011 -
b10000101 +
1%
#1360
0%
#1365
b1101011110100101 !
b1101011110100101 0
b1101011110100101 2
b11111111111111111101011110100101 1
b11111111111010111101001011110011 /
b11101 3
b11010100 &
b11010100 -
b10000110 +
1%
#1370
0%
#1375
b1101010110101010 !
b1101010110101010 0
b1101010110101010 2
b11111111111111111101010110101010 1
b11111111111010101101010100010111 /
b11101 3
b10111101 &
b10111101 -
b10000111 +
1%
#1380
0%
#1385
b1101001110010110 !
b1101001110010110 0
b1101001110010110 2
b11111111111111111101001110010110 1
b11111111111010011100101100000001 /
b11101 3
b10011011 &
b10011011 -
b10001000 +
1%
#1390
0%
#1395
b1101000101101110 !
b1101000101101110 0
b1101000101101110 2
b11111111111111111101000101101110 1
b11111111111010001011011101101010 /
b11101 3
b10101001 &
b10101001 -
b10001001 +
1%
#1400
0%
#1405
b1100111101010111 !
b1100111101010111 0
b1100111101010111 2
b11111111111111111100111101010111 1
b11111111111001111010101110010011 /
b11101 3
b10011111 &
b10011111 -
b10001010 +
1%
#1410
0%
#1415
b1100110101001110 !
b1100110101001110 0
b1100110101001110 2
b11111111111111111100110101001110 1
b11111111111001101010011100010011 /
b11101 3
b10100011 &
b10100011 -
b10001011 +
1%
#1420
0%
#1425
b1100101101011011 !
b1100101101011011 0
b1100101101011011 2
b11111111111111111100101101011011 1
b11111111111001011010110110001101 /
b11101 3
b10111001 &
b10111001 -
b10001100 +
1%
#1430
0%
#1435
b1100100101101100 !
b1100100101101100 0
b1100100101101100 2
b11111111111111111100100101101100 1
b11111111111001001011011000100011 /
b11101 3
b11001000 &
b11001000 -
b10001101 +
1%
#1440
0%
